accustom-1.4.0.dist-info/METADATA
accustom-1.4.0.dist-info/WHEEL
accustom-1.4.0.dist-info/licenses/LICENSE.txt
accustom-1.4.0.dist-info/licenses/NOTICE.txt
accustom/.DS_Store
accustom/Exceptions/__init__.py
accustom/Exceptions/exceptions.py
accustom/Exceptions/py.typed
accustom/__init__.py
accustom/constants.py
accustom/decorators.py
accustom/py.typed
accustom/redaction.py
accustom/response.py
accustom-1.4.0.dist-info/RECORD
