Metadata-Version: 2.1
Name: accustom
Version: 1.4.0
Summary: Accustom is a library for responding to Custom Resources in AWS CloudFormation using the decorator pattern.
Keywords: cloudformation lambda custom resource decorator
Author-Email: Taylor Bertie <bertiet@amazon.com>
License: Apache-2.0
Classifier: Development Status :: 4 - Beta
Classifier: Intended Audience :: Developers
Classifier: License :: OSI Approved :: Apache Software License
Classifier: Programming Language :: Python :: 3
Classifier: Programming Language :: Python :: 3.9
Classifier: Topic :: Software Development :: Libraries :: Application Frameworks
Project-URL: Homepage, https://github.com/awslabs/cloudformation-accustom
Requires-Python: >=3.9
Requires-Dist: boto3~=1.26
Requires-Dist: botocore~=1.29
Requires-Dist: requests~=2.28
Requires-Dist: typing-extensions~=4.5
